llama_index/py.typed
llama_index/vector_stores/typesense/__init__.py
llama_index/vector_stores/typesense/base.py
llama_index_vector_stores_typesense-0.4.0.dist-info/METADATA
llama_index_vector_stores_typesense-0.4.0.dist-info/WHEEL
llama_index_vector_stores_typesense-0.4.0.dist-info/licenses/LICENSE
llama_index_vector_stores_typesense-0.4.0.dist-info/RECORD
